Workbook

Sheet Sources
A2: 來源與假設備註
A3: 官方來源保留在此頁；成本、售價、數量是待替換的工作假設。
A6: 項目 | B6: 內容 | C6: 單位 | D6: 來源類型 | E6: 來源／網址 | F6: 備註
A7: 嘖嘖平台＋金流費 | B7: 8.0%（可修改） | C7: % | D7: 官方平台資訊 | E7: https://www.zeczec.com/docs/funds-rules | F7: 公開資訊約 5.5% 平台費＋約 2.5% 金流費，實際依契約與付款方式為準
A8: 商業登記 | B8: 正式預購／營利交易前建議評估行號 | C8: 制度 | D8: 政府官方 | E8: https://www.gov.tw/News_Content_2_828377 | F8: 商業登記申辦說明
A9: SBIR | B9: 補助資格與上限依最新公告 | C9: 制度 | D9: 政府官方 | E9: https://sbir.sme.gov.tw/ | F9: 是否適用取決於登記狀態與研發計畫
A10: 產品製造成本 | B10: 示例值，請替換 | C10: NT$/件 | D10: 使用者／供應商報價 | F10: 尚未取得正式報價
A11: 包裝、檢測、履約 | B11: 示例值，請替換 | C11: NT$/件 | D11: 工作假設 | F11: 待打樣、跌落測試與物流報價
A12: 售價與首批數量 | B12: 示例值，請替換 | C12: NT$／件、件數 | D12: 工作假設 | F12: 需依學生客群、MOQ 與實測價值修正

Sheet Unit_Economics
A2: 單位經濟
A3: 以產品售價與每件變動成本估算貢獻；價格與成本皆為可替換的初始示例。
A6: 產品 | B6: 預計售價 | C6: 變動成本／件 | D6: 單位貢獻 | E6: 毛利率 | F6: 預計銷售占比 | G6: 加權貢獻
A7: LONG | B7: =Assumptions!B10 -> 2480 | C7: =Assumptions!B17 -> 1530 | D7: =B7-C7 -> 950 | E7: =D7/B7 -> 0.38306452 | F7: =Assumptions!B21 -> 0.6 | G7: =D7*F7 -> 570
A8: ROUND | B8: =Assumptions!B11 -> 2880 | C8: =Assumptions!B18 -> 1730 | D8: =B8-C8 -> 1150 | E8: =D8/B8 -> 0.39930556 | F8: =Assumptions!B22 -> 0.4 | G8: =D8*F8 -> 460
A9: 加權平均 | B9: =B7*F7+B8*F8 -> 2640 | C9: =C7*F7+C8*F8 -> 1610 | D9: =D7*F7+D8*F8 -> 1030 | E9: =D9/B9 -> 0.39015152 | F9: =F7+F8 -> 1 | G9: =G7+G8 -> 1030
A13: 解讀
A14: 單位貢獻 = 售價 − 變動成本。 損益平衡件數以 Summary 的需先準備現金 ÷ 混合貢獻／件估算，實際募資還要依兩款產品的真實訂單組合、平台費、稅務、退貨與交期修正。

Sheet Assumptions
A2: 可修改假設
A3: 黃色底／藍色字為需要替換的初始示例值；所有金額單位為 NT$。
A6: 共通假設 | D6: 募資情境假設
A8: 平台＋金流費率 | B8: 0.08 | D8: 情境 | E8: 用途 | F8: 前置固定費 | G8: LONG 件數 | H8: ROUND 件數 | I8: 預備金率 | J8: 用途說明
A9: 退款／瑕疵預備率 | B9: 0.05 | D9: Lean validation | E9: 學生／老師試用 | F9: 180000 | G9: 10 | H9: 6 | I9: 0.1 | J9: 先驗證需求與適配
A10: LONG 預計售價 | B10: 2480 | D10: Launch ready | E10: 嘖嘖第一輪 | F10: 320000 | G10: 36 | H10: 24 | I10: 0.1 | J10: 含內容、樣品與首批小量
A11: ROUND 預計售價 | B11: 2880 | D11: Production safe | E11: MOQ／交期安全 | F11: 520000 | G11: 120 | H11: 80 | I11: 0.15 | J11: 含較大首批與現金緩衝
A12: LONG 產品製造成本／件 | B12: 1000
A13: ROUND 產品製造成本／件 | B13: 1200
A14: 包裝／件 | B14: 250
A15: 檢測與裝配／件 | B15: 100
A16: 出貨與履約預備／件 | B16: 180
A17: LONG 變動成本／件 | B17: =B12+B14+B15+B16 -> 1530
A18: ROUND 變動成本／件 | B18: =B13+B14+B15+B16 -> 1730
A19: LONG 單位貢獻 | B19: =B10-B17 -> 950
A20: ROUND 單位貢獻 | B20: =B11-B18 -> 1150
A21: 預計 LONG 銷售占比 | B21: 0.6
A22: 預計 ROUND 銷售占比 | B22: =1-B21 -> 0.4
A25: 格式圖例
A26: 藍字＋黃色底 | B26: 需要換成你的真實報價／數量
A27: 黑字 | B27: 同一張表內的計算
A28: 綠字 | B28: 跨工作表連結
A29: 資料狀態 | B29: 初始示例值，不代表正式報價

Sheet Summary
A2: SLAVA 資金準備模型
A3: NT$；初始示例值均可修改，模型用來估算啟動現金與嘖嘖募資目標。
A5: 情境比較
A6: 情境 | B6: 用途 | C6: 前置固定費 | D6: 生產與履約 | E6: 預備金 | F6: 需先準備現金 | G6: 建議募資總額 | H6: 混合貢獻／件 | I6: 損益平衡件數 | J6: 備註
A7: =Assumptions!D9 -> Lean validation | B7: =Assumptions!E9 -> 學生／老師試用 | C7: =Assumptions!F9 -> 180000 | D7: =Assumptions!G9*Assumptions!$B$17+Assumptions!H9*Assumptions!$B$18 -> 25680 | E7: =(C7+D7)*Assumptions!I9 -> 20568 | F7: =C7+D7+E7 -> 226248 | G7: =F7/(1-Assumptions!$B$8) -> 245921.74 | H7: =Assumptions!$B$21*Assumptions!$B$19+Assumptions!$B$22*Assumptions!$B$20 -> 1030 | I7: =F7/H7 -> 219.65825 | J7: 先做驗證，不先大量備貨
A8: =Assumptions!D10 -> Launch ready | B8: =Assumptions!E10 -> 嘖嘖第一輪 | C8: =Assumptions!F10 -> 320000 | D8: =Assumptions!G10*Assumptions!$B$17+Assumptions!H10*Assumptions!$B$18 -> 96600 | E8: =(C8+D8)*Assumptions!I10 -> 41660 | F8: =C8+D8+E8 -> 458260 | G8: =F8/(1-Assumptions!$B$8) -> 498108.7 | H8: =Assumptions!$B$21*Assumptions!$B$19+Assumptions!$B$22*Assumptions!$B$20 -> 1030 | I8: =F8/H8 -> 444.91262 | J8: 建議作為第一輪嘖嘖目標
A9: =Assumptions!D11 -> Production safe | B9: =Assumptions!E11 -> MOQ／交期安全 | C9: =Assumptions!F11 -> 520000 | D9: =Assumptions!G11*Assumptions!$B$17+Assumptions!H11*Assumptions!$B$18 -> 322000 | E9: =(C9+D9)*Assumptions!I11 -> 126300 | F9: =C9+D9+E9 -> 968300 | G9: =F9/(1-Assumptions!$B$8) -> 1052500 | H9: =Assumptions!$B$21*Assumptions!$B$19+Assumptions!$B$22*Assumptions!$B$20 -> 1030 | I9: =F9/H9 -> 940.09709 | J9: MOQ／交期壓力較高時使用
A12: 本輪建議 | F12: 如何使用
A13: 建議先準備現金 | B13: =F8 -> 458260 | F13: 先在 Assumptions 工作表把黃色欄位換成真實報價。 1. 填入兩款產品的單位成本、包裝、檢測與履約預備金。 2. 填入你預計的首批數量與前置製作費。 3. 回到 Summary 看需先準備的現金與嘖嘖募資總額。 這不是會計報表；它是募資前的現金需求與單位經濟估算。
A14: 建議募資總額 | B14: =G8 -> 498108.7
A15: 預計平台／金流費率 | B15: =Assumptions!B8 -> 0.08
A16: 模型限制 | B16: 產品成本、MOQ、運費與售價尚未取得供應商正式報價
